cncmark/__init__.py
cncmark/arc.py
cncmark/config.py
cncmark/edge.py
cncmark/gcode.py
cncmark/line.py
cncmark/point.py
cncmark-0.3.1.dist-info/METADATA
cncmark-0.3.1.dist-info/WHEEL
cncmark-0.3.1.dist-info/RECORD
